hello_googoo/__init__.py
hello_googoo/googoo.py
hello_googoo-0.1.0.dist-info/LICENSE
hello_googoo-0.1.0.dist-info/METADATA
hello_googoo-0.1.0.dist-info/WHEEL
hello_googoo-0.1.0.dist-info/entry_points.txt
hello_googoo-0.1.0.dist-info/top_level.txt
hello_googoo-0.1.0.dist-info/RECORD
