Metadata-Version: 2.1
Name: hello-googoo
Version: 0.1.0
Summary: Google Search via Command Line
Home-page: https://github.com/Florents-Tselai/hello-googoo
Author: Florents Tselai
Author-email: florents@tselai.com
License: BSD
Platform: UNKNOWN
Requires-Dist: bs4 (==0.0.1)
Requires-Dist: lxml (==4.2.6)
Requires-Dist: selenium (==3.141.0)
